test/__init__.py
test/conftest.py
test/test_aio_alibaba.py
test/test_aio_volcengine.py
test/test_api_basic.py
test/test_browser_alibaba.py
test/test_browser_volcengine.py
test/test_cleanup.py
test/test_code_interpreter_alibaba.py
test/test_code_interpreter_aws.py
test/test_code_interpreter_e2b.py
test/test_code_interpreter_volcengine.py
universal_sandbox/__init__.py
universal_sandbox/client.py
universal_sandbox/environment.py
universal_sandbox/raw_client.py
universal_sandbox/aio/__init__.py
universal_sandbox/aio/client.py
universal_sandbox/aio/raw_client.py
universal_sandbox/browser/__init__.py
universal_sandbox/browser/client.py
universal_sandbox/browser/raw_client.py
universal_sandbox/code_interpreter/__init__.py
universal_sandbox/code_interpreter/client.py
universal_sandbox/code_interpreter/raw_client.py
universal_sandbox/core/__init__.py
universal_sandbox/core/api_error.py
universal_sandbox/core/client_wrapper.py
universal_sandbox/core/datetime_utils.py
universal_sandbox/core/file.py
universal_sandbox/core/force_multipart.py
universal_sandbox/core/http_client.py
universal_sandbox/core/http_response.py
universal_sandbox/core/jsonable_encoder.py
universal_sandbox/core/pydantic_utilities.py
universal_sandbox/core/query_encoder.py
universal_sandbox/core/remove_none_from_dict.py
universal_sandbox/core/request_options.py
universal_sandbox/core/serialization.py
universal_sandbox/errors/__init__.py
universal_sandbox/errors/unprocessable_entity_error.py
universal_sandbox/sandboxes/__init__.py
universal_sandbox/sandboxes/client.py
universal_sandbox/sandboxes/raw_client.py
universal_sandbox/tokens/__init__.py
universal_sandbox/tokens/client.py
universal_sandbox/tokens/raw_client.py
universal_sandbox/types/__init__.py
universal_sandbox/types/create_sandbox_request.py
universal_sandbox/types/delete_response.py
universal_sandbox/types/execute_request.py
universal_sandbox/types/execute_response.py
universal_sandbox/types/health_status.py
universal_sandbox-0.0.10.dist-info/METADATA
universal_sandbox-0.0.10.dist-info/WHEEL
universal_sandbox-0.0.10.dist-info/top_level.txt
universal_sandbox-0.0.10.dist-info/RECORD
