Metadata-Version: 2.4
Name: universal-sandbox
Version: 0.0.10
Summary: Python SDK for Universal Sandbox API
Home-page: https://github.com/universal-sandbox/sdk-python
Author: Universal Sandbox
Author-email: support@ai-infra.org
License: MIT
Project-URL: Documentation, https://api.sandbox.ai-infra.org/docs
Project-URL: Source, https://github.com/universal-sandbox/sdk-python
Project-URL: Bug Reports, https://github.com/universal-sandbox/sdk-python/issues
Classifier: Development Status :: 4 - Beta
Classifier: Intended Audience :: Developers
Classifier: License :: OSI Approved :: MIT License
Classifier: Programming Language :: Python :: 3
Classifier: Programming Language :: Python :: 3.8
Classifier: Programming Language :: Python :: 3.9
Classifier: Programming Language :: Python :: 3.10
Classifier: Programming Language :: Python :: 3.11
Classifier: Programming Language :: Python :: 3.12
Requires-Python: >=3.8
Requires-Dist: requests>=2.32.3
Requires-Dist: pydantic>=2.12.0
Dynamic: author
Dynamic: author-email
Dynamic: classifier
Dynamic: description
Dynamic: description-content-type
Dynamic: home-page
Dynamic: license
Dynamic: project-url
Dynamic: requires-dist
Dynamic: requires-python
Dynamic: summary
